LiH.py
LiH-1.0.dist-info/METADATA
LiH-1.0.dist-info/WHEEL
LiH-1.0.dist-info/top_level.txt
LiH-1.0.dist-info/RECORD
