Metadata-Version: 2.1
Name: LiH
Version: 1.0
Summary: This package is for getting started with mathematical modeling
Home-page: https://github.com/Jack-TanXin/LIH
Author: Tan Xin
Author-email: 1792733991@qq.com
License: MIT
Platform: UNKNOWN
